asynctasq_monitor/__init__.py
asynctasq_monitor/__main__.py
asynctasq_monitor/config.py
asynctasq_monitor/py.typed
asynctasq_monitor/api/__init__.py
asynctasq_monitor/api/dependencies.py
asynctasq_monitor/api/main.py
asynctasq_monitor/api/routes/__init__.py
asynctasq_monitor/api/routes/dashboard.py
asynctasq_monitor/api/routes/metrics.py
asynctasq_monitor/api/routes/queues.py
asynctasq_monitor/api/routes/tasks.py
asynctasq_monitor/api/routes/websocket.py
asynctasq_monitor/api/routes/workers.py
asynctasq_monitor/cli/__init__.py
asynctasq_monitor/cli/main.py
asynctasq_monitor/cli/tui.py
asynctasq_monitor/cli/web.py
asynctasq_monitor/models/__init__.py
asynctasq_monitor/models/queue.py
asynctasq_monitor/models/task.py
asynctasq_monitor/models/worker.py
asynctasq_monitor/services/__init__.py
asynctasq_monitor/services/event_consumer.py
asynctasq_monitor/services/metrics_collector.py
asynctasq_monitor/services/prometheus.py
asynctasq_monitor/services/queue_service.py
asynctasq_monitor/services/task_service.py
asynctasq_monitor/services/worker_service.py
asynctasq_monitor/static/index.html
asynctasq_monitor/static/vite.svg
asynctasq_monitor/static/assets/Dashboard-MHUrvgsZ.js
asynctasq_monitor/static/assets/Metrics-CQvleO9p.js
asynctasq_monitor/static/assets/Queues-BFSNsPIY.js
asynctasq_monitor/static/assets/Settings-CIZnqEJ1.js
asynctasq_monitor/static/assets/Tasks-BtuVcUFh.js
asynctasq_monitor/static/assets/Workers-BVtf8ojg.js
asynctasq_monitor/static/assets/activity-BiiKT4VQ.js
asynctasq_monitor/static/assets/api-BHN6AyqB.js
asynctasq_monitor/static/assets/chart-vendor-DrD9aRso.js
asynctasq_monitor/static/assets/circle-check-BT3lGC8x.js
asynctasq_monitor/static/assets/circle-x-CcYernfK.js
asynctasq_monitor/static/assets/clock-CiOYXKHQ.js
asynctasq_monitor/static/assets/index-BYlsIrCB.css
asynctasq_monitor/static/assets/index-DmhZNddw.js
asynctasq_monitor/static/assets/pause-BC559MIv.js
asynctasq_monitor/static/assets/query-vendor-DJBV9M4k.js
asynctasq_monitor-0.9.2.dist-info/METADATA
asynctasq_monitor-0.9.2.dist-info/WHEEL
asynctasq_monitor-0.9.2.dist-info/entry_points.txt
asynctasq_monitor-0.9.2.dist-info/RECORD
