Metadata-Version: 2.4
Name: asynctasq-monitor
Version: 0.9.2
Summary: Real-time monitoring UI for Async TasQ
Project-URL: Homepage, https://github.com/adamrefaey/asynctasq-monitor
Project-URL: Repository, https://github.com/adamrefaey/asynctasq-monitor
Project-URL: Issues, https://github.com/adamrefaey/asynctasq-monitor/issues
Project-URL: Documentation, https://github.com/adamrefaey/asynctasq-monitor#readme
Requires-Python: >=3.12
Requires-Dist: msgpack>=1.1.0
Requires-Dist: pydantic-settings>=2.9.1
Requires-Dist: pydantic>=2.12.5
Requires-Dist: redis[hiredis]>=7.1.0
Requires-Dist: rich>=14.0.0
Requires-Dist: typer>=0.15.0
Provides-Extra: all
Requires-Dist: fastapi[standard]>=0.122.0; extra == 'all'
Requires-Dist: prometheus-client>=0.22.0; extra == 'all'
Requires-Dist: textual>=3.3.0; extra == 'all'
Provides-Extra: tui
Requires-Dist: textual>=3.3.0; extra == 'tui'
Provides-Extra: web
Requires-Dist: fastapi[standard]>=0.122.0; extra == 'web'
Requires-Dist: prometheus-client>=0.22.0; extra == 'web'
